pythonLock/__init__.py
pythonLock/main.py
pythonLock-1.0.dist-info/LICENSE
pythonLock-1.0.dist-info/METADATA
pythonLock-1.0.dist-info/WHEEL
pythonLock-1.0.dist-info/top_level.txt
pythonLock-1.0.dist-info/RECORD
