Metadata-Version: 2.2
Name: pythonLock
Version: 1.0
Summary: Package to used for handling lock mechanism when running appplication with multiple replicas
Author: Tanmay Varade
Author-email: tanmayvarade235@gmail.com
Keywords: python,distributed,lock,rds,sql,redis,replicas,kubernetes
License-File: LICENSE
Requires-Dist: APScheduler
Requires-Dist: mysql-connector-python
Requires-Dist: redis
Requires-Dist: requests
Dynamic: author
Dynamic: author-email
Dynamic: description
Dynamic: description-content-type
Dynamic: keywords
Dynamic: requires-dist
Dynamic: summary
